{"cameraMode":{"drawMode":0,"name":"Shaded","section":"Shading Mode"},"sceneLighting":true,"audioPlay":false,"sceneViewState":{"showFog":true,"showMaterialUpdate":false,"showSkybox":true,"showFlares":true,"showImageEffects":true,"showParticleSystems":true},"in2DMode":false,"pivot":{"x":19.598913192749025,"y":5.356779098510742,"z":157.4080352783203},"rotation":{"x":-0.06026972085237503,"y":0.01257241703569889,"z":-0.0008007113356143236,"w":-0.9981269240379334},"size":0.054256558418273929,"orthographic":false}